{
  "name": "asegstatsdiff",
  "tool-version": "7.4.1",
  "description": "Compute and report percentage differences in aseg morphometry data between two subjects.",
  "command-line": "asegstatsdiff [SUBJECT1] [SUBJECT2][OUTDIR]",
  "schema-version": "0.5",
  "inputs": [
    {
      "description": "The first subject to be compared.",
      "value-key": "[SUBJECT1]",
      "type": "String",
      "optional": false,
      "id": "subject1",
      "name": "Subject 1"
    },
    {
      "description": "The second subject to be compared.",
      "value-key": "[SUBJECT2]",
      "type": "String",
      "optional": false,
      "id": "subject2",
      "name": "Subject 2"
    },
    {
      "command-line-flag": "",
      "description": "Optionally specify a directory to write the output asegstats.txt.",
      "value-key": "[OUTDIR]",
      "type": "String",
      "optional": true,
      "id": "outdir",
      "name": "Output Directory"
    }
  ],
  "output-files": [
    {
      "path-template": "[OUTDIR]/asegstats.txt",
      "description": "Output table with percent differences added.",
      "optional": false,
      "id": "asegstats_output",
      "name": "Asegstats Output"
    }
  ],
  "author": "FreeSurfer Developers",
  "container-image": {
    "type": "docker",
    "image": "freesurfer/freesurfer:7.4.1"
  },
  "url": "https://github.com/freesurfer/freesurfer"
}
