{
  "tool-version": "7.4.1",
  "name": "mris_errors",
  "description": "This program will unfold an MRI on the surface of an ellipsoid.",
  "command-line": "mris_errors [OPTIONS] [INPUT_IMAGE_FILE]",
  "schema-version": "0.5",
  "inputs": [
    {
      "description": "Input image file.",
      "value-key": "[INPUT_IMAGE_FILE]",
      "type": "File",
      "optional": false,
      "id": "input_image_file",
      "name": "Input image file"
    }
  ],
  "author": "FreeSurfer Developers",
  "container-image": {
    "type": "docker",
    "image": "freesurfer/freesurfer:7.4.1"
  },
  "url": "https://github.com/freesurfer/freesurfer"
}
