{
  "name": "mris_volmask_vtk",
  "description": "Computes a volume mask at the resolution of the brain.mgz file, containing labels for various brain structures using surface files.",
  "command-line": "mris_volmask [CAP_DISTANCE] [LABEL_BACKGROUND] [LABEL_LEFT_WHITE] [LABEL_LEFT_RIBBON] [LABEL_RIGHT_WHITE] [LABEL_RIGHT_RIBBON] [SURF_WHITE] [SURF_PIAL] [ASEG_NAME] [OUT_ROOT] [SUBJECTS_DIR] [SAVE_DISTANCE] [LH_ONLY] [RH_ONLY] [PARALLEL] [EDIT_ASEG] [SAVE_RIBBON] [IO_PARAM]",
  "schema-version": "0.5",
  "inputs": [
    {
      "command-line-flag": "--cap_distance",
      "description": "Maximum distance up to which the signed distance function computation is accurate.",
      "value-key": "[CAP_DISTANCE]",
      "type": "Number",
      "optional": true,
      "id": "cap_distance",
      "name": "Cap Distance"
    },
    {
      "command-line-flag": "--label_background",
      "description": "Override the default background label value (0).",
      "value-key": "[LABEL_BACKGROUND]",
      "type": "Number",
      "optional": true,
      "id": "label_background",
      "name": "Background Label"
    },
    {
      "command-line-flag": "--label_left_white",
      "description": "Override the default left white matter label (20).",
      "value-key": "[LABEL_LEFT_WHITE]",
      "type": "Number",
      "optional": true,
      "id": "label_left_white",
      "name": "Left White Matter Label"
    },
    {
      "command-line-flag": "--label_left_ribbon",
      "description": "Override the default left ribbon label (10).",
      "value-key": "[LABEL_LEFT_RIBBON]",
      "type": "Number",
      "optional": true,
      "id": "label_left_ribbon",
      "name": "Left Ribbon Label"
    },
    {
      "command-line-flag": "--label_right_white",
      "description": "Override the default right white matter label (120).",
      "value-key": "[LABEL_RIGHT_WHITE]",
      "type": "Number",
      "optional": true,
      "id": "label_right_white",
      "name": "Right White Matter Label"
    },
    {
      "command-line-flag": "--label_right_ribbon",
      "description": "Override the default right ribbon label (110).",
      "value-key": "[LABEL_RIGHT_RIBBON]",
      "type": "Number",
      "optional": true,
      "id": "label_right_ribbon",
      "name": "Right Ribbon Label"
    },
    {
      "command-line-flag": "--surf_white",
      "description": "Surface root name for white matter surfaces (default: white).",
      "value-key": "[SURF_WHITE]",
      "type": "String",
      "optional": true,
      "id": "surf_white",
      "name": "White Surface Name"
    },
    {
      "command-line-flag": "--surf_pial",
      "description": "Surface root name for pial surfaces (default: pial).",
      "value-key": "[SURF_PIAL]",
      "type": "String",
      "optional": true,
      "id": "surf_pial",
      "name": "Pial Surface Name"
    },
    {
      "command-line-flag": "--aseg_name",
      "description": "Specify a different name for the aseg input file (default: aseg).",
      "value-key": "[ASEG_NAME]",
      "type": "String",
      "optional": true,
      "id": "aseg_name",
      "name": "Aseg Name"
    },
    {
      "command-line-flag": "--out_root",
      "description": "Output root name (default: ribbon) for generated output files.",
      "value-key": "[OUT_ROOT]",
      "type": "String",
      "optional": true,
      "id": "out_root",
      "name": "Output Root"
    },
    {
      "command-line-flag": "--sd",
      "description": "Specify the SUBJECTS_DIR, default is read from environment.",
      "value-key": "[SUBJECTS_DIR]",
      "type": "String",
      "optional": true,
      "id": "subjects_dir",
      "name": "Subjects Directory"
    },
    {
      "command-line-flag": "--save_distance",
      "description": "Option to save the signed distance function.",
      "value-key": "[SAVE_DISTANCE]",
      "type": "Flag",
      "optional": true,
      "id": "save_distance",
      "name": "Save Distance Function Flag"
    },
    {
      "command-line-flag": "--lh-only",
      "description": "Only process left hemisphere.",
      "value-key": "[LH_ONLY]",
      "type": "Flag",
      "optional": true,
      "id": "lh_only",
      "name": "Left Hemisphere Only Flag"
    },
    {
      "command-line-flag": "--rh-only",
      "description": "Only process right hemisphere.",
      "value-key": "[RH_ONLY]",
      "type": "Flag",
      "optional": true,
      "id": "rh_only",
      "name": "Right Hemisphere Only Flag"
    },
    {
      "command-line-flag": "--parallel",
      "description": "Run hemispheres in parallel and combine the result.",
      "value-key": "[PARALLEL]",
      "type": "Flag",
      "optional": true,
      "id": "parallel",
      "name": "Parallel Processing Flag"
    },
    {
      "command-line-flag": "--edit_aseg",
      "description": "Edit the aseg using the ribbons and save it.",
      "value-key": "[EDIT_ASEG]",
      "type": "Flag",
      "optional": true,
      "id": "edit_aseg",
      "name": "Edit Aseg Flag"
    },
    {
      "command-line-flag": "--save_ribbon",
      "description": "Save only the ribbon for the hemispheres.",
      "value-key": "[SAVE_RIBBON]",
      "type": "Flag",
      "optional": true,
      "id": "save_ribbon",
      "name": "Save Ribbon Flag"
    },
    {
      "description": "Input-Output parameter as positional argument",
      "value-key": "[IO_PARAM]",
      "type": "String",
      "optional": false,
      "id": "io_param",
      "name": "IO Parameter"
    }
  ],
  "output-files": [
    {
      "path-template": "mri/[OUT_ROOT].mgz",
      "description": "Output volume mask file.",
      "optional": true,
      "id": "output_volume_mask",
      "name": "Output Volume Mask File"
    },
    {
      "path-template": "mri/lh.[OUT_ROOT].mgz",
      "description": "Left hemisphere ribbon output file.",
      "optional": true,
      "id": "left_ribbon_output",
      "name": "Left Ribbon Output File"
    },
    {
      "path-template": "mri/rh.[OUT_ROOT].mgz",
      "description": "Right hemisphere ribbon output file.",
      "optional": true,
      "id": "right_ribbon_output",
      "name": "Right Ribbon Output File"
    },
    {
      "path-template": "mri/aseg.ribbon.mgz",
      "description": "Edited aseg output using ribbons.",
      "optional": true,
      "id": "edited_aseg_output",
      "name": "Edited Aseg Output File"
    },
    {
      "path-template": "mri/?h.dwhite.mgz",
      "description": "Signed distance output for the white matter.",
      "optional": true,
      "id": "dwhite_output",
      "name": "Distance White Output File"
    },
    {
      "path-template": "mri/?h.dpial.mgz",
      "description": "Signed distance output for the pial surface.",
      "optional": true,
      "id": "dpial_output",
      "name": "Distance Pial Output File"
    }
  ],
  "container-image": {
    "type": "docker",
    "image": "freesurfer/freesurfer:7.4.1"
  },
  "author": "FreeSurfer Developers",
  "tool-version": "7.4.1",
  "descriptor-url": "https://github.com/freesurfer/freesurfer",
  "url": "https://github.com/freesurfer/freesurfer"
}
