{
  "tool-version": "7.4.1",
  "name": "talairach2",
  "author": "FreeSurfer Developers",
  "description": "Tool for processing and converting talairach transformation files.",
  "command-line": "talairach2 [SUBJECT_ID] [MGZ_FLAG]",
  "schema-version": "0.5",
  "inputs": [
    {
      "description": "Subject identifier for the talairach transformation.",
      "value-key": "[SUBJECT_ID]",
      "type": "String",
      "optional": false,
      "id": "subject_id",
      "name": "Subject ID"
    },
    {
      "description": "Flag to indicate whether mgz format is used.",
      "value-key": "[MGZ_FLAG]",
      "type": "String",
      "optional": true,
      "id": "mgz_flag",
      "name": "MGZ Flag"
    }
  ],
  "container-image": {
    "type": "docker",
    "image": "freesurfer/freesurfer:7.4.1"
  },
  "url": "https://github.com/freesurfer/freesurfer"
}