{
  "tool-version": "23.1.10",
  "name": "1dcat",
  "author": "AFNI Team",
  "descriptor-url": "https://afni.nimh.nih.gov/pub/dist/doc/program_help/1dcat.html",
  "description": "Concatenates columns of multiple 1D or TSV/CSV files",
  "url": "https://afni.nimh.nih.gov/pub/dist/doc/program_help/1dcat.html",
  "command-line": "1dcat [OPTIONS] [INPUT_FILES]",
  "container-image": {
    "image": "fcpindi/c-pac:latest",
    "type": "docker"
  },
  "inputs": [
    {
      "description": "Input 1D or TSV/CSV files to concatenate",
      "value-key": "[INPUT_FILES]",
      "type": "File",
      "optional": false,
      "id": "input_files",
      "name": "Input files",
      "list": true
    },
    {
      "command-line-flag": "-tsvout",
      "description": "Output in TSV format with tabs as separators and a header line",
      "value-key": "[TSV_OUTPUT_FLAG]",
      "type": "Flag",
      "optional": true,
      "id": "tsv_output",
      "name": "TSV format output"
    },
    {
      "command-line-flag": "-csvout",
      "description": "Output in CSV format with commas as separators and a header line",
      "value-key": "[CSV_OUTPUT_FLAG]",
      "type": "Flag",
      "optional": true,
      "id": "csv_output",
      "name": "CSV format output"
    },
    {
      "command-line-flag": "-nonconst",
      "description": "Omit columns that are identically constant from the output",
      "value-key": "[NONCONST_OUTPUT_FLAG]",
      "type": "Flag",
      "optional": true,
      "id": "nonconst_output",
      "name": "Non-constant columns output"
    },
    {
      "command-line-flag": "-nonfixed",
      "description": "Keep only columns marked as 'free' in the 3dAllineate header",
      "value-key": "[NONFIXED_OUTPUT_FLAG]",
      "type": "Flag",
      "optional": true,
      "id": "nonfixed_output",
      "name": "Non-fixed columns output"
    },
    {
      "command-line-flag": "-form",
      "description": "Specify the format of the numbers to be output",
      "value-key": "[NUMBER_FORMAT]",
      "type": "String",
      "optional": true,
      "id": "number_format",
      "name": "Number format"
    },
    {
      "command-line-flag": "-stack",
      "description": "Stack the columns of the resulting matrix in the output",
      "value-key": "[STACK_OUTPUT_FLAG]",
      "type": "Flag",
      "optional": true,
      "id": "stack_output",
      "name": "Stack columns output"
    },
    {
      "command-line-flag": "-sel",
      "description": "Apply the same column/row selection string to all filenames on the command line",
      "value-key": "[COLUMN_ROW_SELECTION]",
      "type": "String",
      "optional": true,
      "id": "column_row_selection",
      "name": "Column/Row selection"
    },
    {
      "command-line-flag": "-OKempty",
      "description": "Exit quietly when encountering an empty file on disk",
      "value-key": "[OK_EMPTY_FLAG]",
      "type": "Flag",
      "optional": true,
      "id": "ok_empty",
      "name": "OK empty files"
    }
  ],
  "schema-version": "0.5",
  "output-files": [
    {
      "path-template": "stdout",
      "description": "Concatenated output in specified format",
      "optional": false,
      "id": "concatenated_output",
      "name": "Concatenated Output"
    }
  ]
}
