{
  "tool-version": "May, 2013",
  "name": "@simulate_motion",
  "author": "AFNI Team",
  "description": "Create simulated motion time series in an EPI dataset based on the provided motion parameters and an input volume.",
  "command-line": "@simulate_motion [options] -epi [EPI_DSET] -motion_file [MOTION_PARAMS]",
  "inputs": [
    {
      "description": "Input EPI volume or time series (only a volreg base is needed, though more is okay).",
      "value-key": "[EPI_DSET]",
      "type": "File",
      "optional": false,
      "id": "epi",
      "name": "EPI dataset",
      "command-line-flag": "-epi"
    },
    {
      "description": "Motion parameter file (as output by 3dvolreg).",
      "value-key": "[MOTION_PARAMS]",
      "type": "File",
      "optional": false,
      "id": "motion_file",
      "name": "Motion parameters file",
      "command-line-flag": "-motion_file"
    },
    {
      "description": "Provide EPI dataset with slice timing.",
      "value-key": "[EPI_TIMING]",
      "type": "File",
      "optional": true,
      "id": "epi_timing",
      "name": "EPI timing dataset",
      "command-line-flag": "-epi_timing"
    },
    {
      "description": "Prefix for data results (default = motion_sim.NUM_TRS).",
      "value-key": "[PREFIX]",
      "type": "String",
      "optional": true,
      "id": "prefix",
      "name": "Prefix for results",
      "command-line-flag": "-prefix"
    },
    {
      "description": "Do not remove the 'work' directory.",
      "value-key": "[SAVE_WORKDIR]",
      "type": "Flag",
      "optional": true,
      "id": "save_workdir",
      "name": "Save work directory",
      "command-line-flag": "-save_workdir"
    },
    {
      "description": "Only test running the program, do not create a simulated motion dataset.",
      "value-key": "[TEST]",
      "type": "Flag",
      "optional": true,
      "id": "test",
      "name": "Test mode",
      "command-line-flag": "-test"
    },
    {
      "description": "Specify a verbose level (default = 1).",
      "value-key": "[VERB_LEVEL]",
      "type": "Number",
      "optional": true,
      "id": "verb_level",
      "name": "Verbose level",
      "command-line-flag": "-verb"
    },
    {
      "description": "0-based index of volreg base in EPI dataset.",
      "value-key": "[VR_BASE]",
      "type": "Number",
      "optional": true,
      "id": "vr_base",
      "name": "Volreg base index",
      "command-line-flag": "-vr_base"
    },
    {
      "description": "Specify a method for forward alignment/transform.",
      "value-key": "[WARP_METHOD]",
      "type": "String",
      "optional": true,
      "id": "warp_method",
      "name": "Warp method",
      "command-line-flag": "-warp_method"
    },
    {
      "description": "Specify a 12 parameter affine transformation.",
      "value-key": "[WARP_1D]",
      "type": "File",
      "optional": true,
      "id": "warp_1D",
      "name": "Affine transformation file",
      "command-line-flag": "-warp_1D"
    },
    {
      "description": "Specify a grid master dataset for the -warp_1D transform.",
      "value-key": "[WARP_MASTER]",
      "type": "File",
      "optional": true,
      "id": "warp_master",
      "name": "Warp master dataset",
      "command-line-flag": "-warp_master"
    },
    {
      "description": "Use wsinc5 interpolation in 3dAllineate.",
      "value-key": "[WSINC5]",
      "type": "Flag",
      "optional": true,
      "id": "wsinc5",
      "name": "wsinc5 interpolation",
      "command-line-flag": "-wsinc5"
    },
    {
      "description": "Show help message.",
      "value-key": "[HELP]",
      "type": "Flag",
      "optional": true,
      "id": "help",
      "name": "Help",
      "command-line-flag": "-help"
    },
    {
      "description": "Show program modification history.",
      "value-key": "[HIST]",
      "type": "Flag",
      "optional": true,
      "id": "hist",
      "name": "History",
      "command-line-flag": "-hist"
    },
    {
      "description": "Show current todo list.",
      "value-key": "[TODO]",
      "type": "Flag",
      "optional": true,
      "id": "todo",
      "name": "Todo list",
      "command-line-flag": "-todo"
    },
    {
      "description": "Show program version.",
      "value-key": "[VER]",
      "type": "Flag",
      "optional": true,
      "id": "ver",
      "name": "Version",
      "command-line-flag": "-ver"
    }
  ],
  "schema-version": "0.5",
  "output-files": [
    {
      "path-template": "[PREFIX]_simulated_motion.nii.gz",
      "description": "Motion simulated EPI time series",
      "optional": true,
      "id": "simulated_motion_output",
      "name": "Simulated motion output"
    }
  ],
  "container-image": {
    "image": "fcpindi/c-pac:latest",
    "type": "docker"
  },
  "url": "https://afni.nimh.nih.gov/pub/dist/doc/program_help/@simulate_motion.html"
}
