{
  "tool-version": "24.2.06",
  "name": "adjunct_calc_mont_dims.py",
  "author": "AFNI Developers",
  "description": "A helper function for the fat_proc* scripts",
  "command-line": "adjunct_calc_mont_dims.py [HELP]",
  "inputs": [
    {
      "command-line-flag": "-help",
      "description": "Display help information",
      "value-key": "[HELP]",
      "type": "Flag",
      "optional": true,
      "id": "help",
      "name": "Help Flag"
    }
  ],
  "schema-version": "0.5",
  "container-image": {
    "type": "docker",
    "image": "afni/afni_make_build:AFNI_24.2.06"
  },
  "url": "https://afni.nimh.nih.gov/"
}
